mcp_openstack_http/__init__.py
mcp_openstack_http/__main__.py
mcp_openstack_http/os_compute_service.py
mcp_openstack_http/os_image.py
mcp_openstack_http/os_network.py
mcp_openstack_http/os_network_agent.py
mcp_openstack_http/os_server.py
mcp_openstack_http/os_service.py
mcp_openstack_http/os_volume.py
mcp_openstack_http/os_volume_service.py
mcp_openstack_http/server.py
openstack_mcp_server-0.1.1.dist-info/METADATA
openstack_mcp_server-0.1.1.dist-info/WHEEL
openstack_mcp_server-0.1.1.dist-info/entry_points.txt
openstack_mcp_server-0.1.1.dist-info/top_level.txt
openstack_mcp_server-0.1.1.dist-info/RECORD
