Metadata-Version: 2.4
Name: openstack-mcp-server
Version: 0.1.1
Summary: 获取OpenStack集群环境资源信息，包括计算、存储、网络、镜像等资源
Classifier: Development Status :: 4 - Beta
Classifier: Programming Language :: Python :: 3
Classifier: Programming Language :: Python :: 3.10
Classifier: Programming Language :: Python :: 3.11
Classifier: Intended Audience :: System Administrators
Classifier: Topic :: System :: Systems Administration
Requires-Python: >=3.10
Requires-Dist: httpx>=0.28.1
Requires-Dist: mcp>=1.9.4
Requires-Dist: click>=8.1.0
Requires-Dist: anyio>=3.7.0
Requires-Dist: starlette>=0.28.0
Requires-Dist: uvicorn>=0.23.0
Requires-Dist: openstacksdk>=1.4.0
